.editorconfig
.gitattributes
.gitignore
.readthedocs.yaml
BUILDNOTES.txt
LICENSE
LICENSES-thirdparty.md
README.md
environment.yml
pyproject.toml
requirements.txt
runtest.py
.github/workflows/python-package.yml
conda_recipe/conda_build_config.yaml
conda_recipe/meta.yaml
dev_tools/_docstring_config.py
dev_tools/docstring_filters.txt
dev_tools/docstring_xfails.txt
dev_tools/gen_requirements.py
dev_tools/validate_docstrings.py
docs/CONTRIBUTING.md
docs/Makefile
docs/THREADING.md
docs/environment.yml
docs/make.bat
docs/source/benchmarking.rst
docs/source/conf.py
docs/source/index.rst
docs/source/_autoapi_templates/python/module.rst
docs/source/_autoapi_templates/python/package.rst
docs/source/_static/.keep
docs/source/_static/cross-join-graphic.png
docs/source/_static/index_api.svg
docs/source/_static/index_getting_started.svg
docs/source/_static/riptable.css
docs/source/_static/riptable_logo.PNG
docs/source/tutorial/RiptableExercises.ipynb
docs/source/tutorial/RiptableSolutions.ipynb
docs/source/tutorial/categoricals_user_guide.rst
docs/source/tutorial/categoricals_user_guide_access_data.rst
docs/source/tutorial/categoricals_user_guide_base_index.rst
docs/source/tutorial/categoricals_user_guide_bins_categories.rst
docs/source/tutorial/categoricals_user_guide_comparisons.rst
docs/source/tutorial/categoricals_user_guide_construct.rst
docs/source/tutorial/categoricals_user_guide_dtype.rst
docs/source/tutorial/categoricals_user_guide_filters.rst
docs/source/tutorial/categoricals_user_guide_indexing.rst
docs/source/tutorial/categoricals_user_guide_invalid_categories.rst
docs/source/tutorial/categoricals_user_guide_order.rst
docs/source/tutorial/cross_join_using_merge2.rst
docs/source/tutorial/output_11_0.png
docs/source/tutorial/output_13_0.png
docs/source/tutorial/output_15_0.png
docs/source/tutorial/output_25_0.png
docs/source/tutorial/output_27_0.png
docs/source/tutorial/perf-may-suffer.png
docs/source/tutorial/rt_autocomplete.png
riptable.egg-info/PKG-INFO
riptable.egg-info/SOURCES.txt
riptable.egg-info/dependency_links.txt
riptable.egg-info/requires.txt
riptable.egg-info/top_level.txt
