Metadata-Version: 2.1
Name: riptable
Version: 1.17.1
Summary: Python Package for riptable studies framework
Author-email: RTOS Holdings <rtosholdings-bot@sig.com>
License: BSD 3-Clause+Patent License
Project-URL: Repository, https://github.com/rtosholdings/riptable
Project-URL: Documentation, https://riptable.readthedocs.io/en/stable/
Classifier: Development Status :: 4 - Beta
Classifier: Programming Language :: Python :: 3
Classifier: Programming Language :: Python :: 3.10
Classifier: Programming Language :: Python :: 3.11
Classifier: Programming Language :: Python :: 3.12
Classifier: License :: OSI Approved :: BSD License
Classifier: Operating System :: OS Independent
Requires-Python: >=3.10
License-File: LICENSE
License-File: LICENSES-thirdparty.md
Requires-Dist: ansi2html>=1.5.2
Requires-Dist: numba>=0.56.2
Requires-Dist: numpy>=1.23
Requires-Dist: pandas<3.0,>=1.0
Requires-Dist: python-dateutil
Requires-Dist: riptide_cpp<2,>=1.19.0
Requires-Dist: typing-extensions>=4.9.0
